statespacecheck/__init__.py
statespacecheck/_validation.py
statespacecheck/_version.py
statespacecheck/highest_density.py
statespacecheck/periods.py
statespacecheck/predictive_checks.py
statespacecheck/state_consistency.py
statespacecheck/viz.py
statespacecheck-0.1.0.dist-info/METADATA
statespacecheck-0.1.0.dist-info/WHEEL
statespacecheck-0.1.0.dist-info/licenses/LICENSE
statespacecheck-0.1.0.dist-info/RECORD
