Metadata-Version: 2.4
Name: statespacecheck
Version: 0.1.0
Summary: Goodness-of-fit diagnostics for state space models
Project-URL: Homepage, https://edeno.github.io/statespacecheck
Project-URL: Documentation, https://edeno.github.io/statespacecheck
Project-URL: Repository, https://github.com/edeno/statespacecheck
Project-URL: Issues, https://github.com/edeno/statespacecheck/issues
Project-URL: Changelog, https://github.com/edeno/statespacecheck/releases
Author-email: Eric Denovellis <eric.denovellis@ucsf.edu>, Sirui Zeng <zengsr@bu.edu>, "Uri T. Eden" <tzvi@bu.edu>
License: MIT License
License-File: LICENSE
Keywords: bayesian,diagnostics,goodness-of-fit,kalman-filter,neuroscience,state-space-models
Classifier: Development Status :: 4 - Beta
Classifier: Intended Audience :: Science/Research
Classifier: License :: OSI Approved :: MIT License
Classifier: Operating System :: OS Independent
Classifier: Programming Language :: Python :: 3
Classifier: Programming Language :: Python :: 3.10
Classifier: Programming Language :: Python :: 3.11
Classifier: Programming Language :: Python :: 3.12
Classifier: Programming Language :: Python :: 3.13
Classifier: Topic :: Scientific/Engineering
Classifier: Topic :: Scientific/Engineering :: Mathematics
Classifier: Topic :: Scientific/Engineering :: Medical Science Apps.
Classifier: Typing :: Typed
Requires-Python: >=3.10
Requires-Dist: matplotlib>=3.8.0
Requires-Dist: numpy>=1.26.0
Requires-Dist: scipy>=1.11.0
Provides-Extra: dev
Requires-Dist: hypothesis>=6.0.0; extra == 'dev'
Requires-Dist: mypy>=1.13.0; extra == 'dev'
Requires-Dist: pre-commit>=4.0.0; extra == 'dev'
Requires-Dist: pytest-cov>=6.0.0; extra == 'dev'
Requires-Dist: pytest>=8.0.0; extra == 'dev'
Requires-Dist: ruff>=0.8.0; extra == 'dev'
Provides-Extra: docs
Requires-Dist: jupytext>=1.16.0; extra == 'docs'
Requires-Dist: mkdocs-gen-files>=0.5.0; extra == 'docs'
Requires-Dist: mkdocs-jupyter>=0.25.0; extra == 'docs'
Requires-Dist: mkdocs-literate-nav>=0.6.0; extra == 'docs'
Requires-Dist: mkdocs-material>=9.5.0; extra == 'docs'
Requires-Dist: mkdocs-section-index>=0.3.0; extra == 'docs'
Requires-Dist: mkdocs>=1.6.0; extra == 'docs'
Requires-Dist: mkdocstrings[python]>=0.26.0; extra == 'docs'
